qgui/__init__.py
qgui/__main__.py
qgui/banner_tools.py
qgui/base_frame.py
qgui/base_tools.py
qgui/factory.py
qgui/manager.py
qgui/notebook_tools.py
qgui/os_tools.py
qgui/resources/demo/panda.jpg
qgui/resources/icon/double_down.png
qgui/resources/icon/double_up.png
qgui/resources/icon/github.png
qgui/resources/icon/play_w.png
qgui/resources/icon/up_cloud.png
qgui/theme/ttkbootstrap_themes.json
qgui/third_party/__init__.py
qgui/third_party/collapsing_frame.py
QGUI_fixed-0.5.dist-info/LICENSE
QGUI_fixed-0.5.dist-info/METADATA
QGUI_fixed-0.5.dist-info/WHEEL
QGUI_fixed-0.5.dist-info/top_level.txt
QGUI_fixed-0.5.dist-info/RECORD
