Metadata-Version: 2.1
Name: QGUI-fixed
Version: 0.5
Summary: QGUI - 0.1MB超轻量Python GUI框架，用模板来快捷制作深度学习模型推理界面 
Home-page: https://github.com/QPT-Family/QGUI
Author: GT-ZhangAcer
Author-email: zhangacer@foxmail.com
License: MIT
Platform: UNKNOWN
Requires-Python: >3.5
License-File: LICENSE
Requires-Dist: ttkbootstrap
Requires-Dist: pillow
